{
	"trigger": true,
	"modules": ["add-to-group"],
	"parentResource": "DeenDownAuth",
	"functionName": "DeenDownAuthPostConfirmation",
	"resourceName": "DeenDownAuthPostConfirmation",
	"parentStack": "auth",
	"triggerEnvs": "[]",
	"triggerDir": "/snapshot/amplify-cli/build/node_modules/@aws-amplify/amplify-category-auth/provider-utils/awscloudformation/triggers/PostConfirmation",
	"triggerTemplate": "PostConfirmation.json.ejs",
	"triggerEventPath": "PostConfirmation.event.json",
	"roleName": "DeenDownAuthPostConfirmation",
	"skipEdit": true
}
